fluidpy/__init__.py
fluidpy/fluidnc.py
fluidpy/udecimal.py
fluidpy-0.2.0.dist-info/METADATA
fluidpy-0.2.0.dist-info/WHEEL
fluidpy-0.2.0.dist-info/top_level.txt
fluidpy-0.2.0.dist-info/RECORD
