Metadata-Version: 2.4
Name: fluidpy
Version: 0.2.0
Summary: Library to interact with FluidNC's channel protocol.
Requires-Python: >=3.10.0
Requires-Dist: pyserial>=3.5
